pyqt6_without_qt/QtBluetooth.abi3.so
pyqt6_without_qt/QtBluetooth.pyi
pyqt6_without_qt/QtCore.abi3.so
pyqt6_without_qt/QtCore.pyi
pyqt6_without_qt/QtDBus.abi3.so
pyqt6_without_qt/QtDBus.pyi
pyqt6_without_qt/QtDesigner.abi3.so
pyqt6_without_qt/QtDesigner.pyi
pyqt6_without_qt/QtGui.abi3.so
pyqt6_without_qt/QtGui.pyi
pyqt6_without_qt/QtHelp.abi3.so
pyqt6_without_qt/QtHelp.pyi
pyqt6_without_qt/QtMultimedia.abi3.so
pyqt6_without_qt/QtMultimedia.pyi
pyqt6_without_qt/QtMultimediaWidgets.abi3.so
pyqt6_without_qt/QtMultimediaWidgets.pyi
pyqt6_without_qt/QtNetwork.abi3.so
pyqt6_without_qt/QtNetwork.pyi
pyqt6_without_qt/QtNfc.abi3.so
pyqt6_without_qt/QtNfc.pyi
pyqt6_without_qt/QtOpenGL.abi3.so
pyqt6_without_qt/QtOpenGL.pyi
pyqt6_without_qt/QtOpenGLWidgets.abi3.so
pyqt6_without_qt/QtOpenGLWidgets.pyi
pyqt6_without_qt/QtPdf.abi3.so
pyqt6_without_qt/QtPdf.pyi
pyqt6_without_qt/QtPdfWidgets.abi3.so
pyqt6_without_qt/QtPdfWidgets.pyi
pyqt6_without_qt/QtPositioning.abi3.so
pyqt6_without_qt/QtPositioning.pyi
pyqt6_without_qt/QtPrintSupport.abi3.so
pyqt6_without_qt/QtPrintSupport.pyi
pyqt6_without_qt/QtQml.abi3.so
pyqt6_without_qt/QtQml.pyi
pyqt6_without_qt/QtQuick.abi3.so
pyqt6_without_qt/QtQuick.pyi
pyqt6_without_qt/QtQuick3D.abi3.so
pyqt6_without_qt/QtQuick3D.pyi
pyqt6_without_qt/QtQuickWidgets.abi3.so
pyqt6_without_qt/QtQuickWidgets.pyi
pyqt6_without_qt/QtRemoteObjects.abi3.so
pyqt6_without_qt/QtRemoteObjects.pyi
pyqt6_without_qt/QtSensors.abi3.so
pyqt6_without_qt/QtSensors.pyi
pyqt6_without_qt/QtSerialPort.abi3.so
pyqt6_without_qt/QtSerialPort.pyi
pyqt6_without_qt/QtSpatialAudio.abi3.so
pyqt6_without_qt/QtSpatialAudio.pyi
pyqt6_without_qt/QtSql.abi3.so
pyqt6_without_qt/QtSql.pyi
pyqt6_without_qt/QtSvg.abi3.so
pyqt6_without_qt/QtSvg.pyi
pyqt6_without_qt/QtSvgWidgets.abi3.so
pyqt6_without_qt/QtSvgWidgets.pyi
pyqt6_without_qt/QtTest.abi3.so
pyqt6_without_qt/QtTest.pyi
pyqt6_without_qt/QtTextToSpeech.abi3.so
pyqt6_without_qt/QtTextToSpeech.pyi
pyqt6_without_qt/QtWebChannel.abi3.so
pyqt6_without_qt-6.7.1.post1.dist-info/METADATA
pyqt6_without_qt-6.7.1.post1.dist-info/WHEEL
pyqt6_without_qt-6.7.1.post1.dist-info/entry_points.txt
pyqt6_without_qt-6.7.1.post1.dist-info/RECORD
