Metadata-Version: 2.1
Name: pyqt6-without-qt
Version: 6.7.1.post1
Requires-Python: >=3.8
Summary: Python bindings for the Qt cross platform application toolkit
Project-Url: homepage, https://github.com/maresb/pyqt6-without-qt
Requires-Dist: PyQt6-sip (>=13.8, <14)
License: GPL v3
Author-Email: Ben Mares <services-pyqt6-without-qt@tensorial.com>
